irie/__init__.py
irie/__main__.py
irie/maps.py
irie/apps/__init__.py
irie/apps/config.py
irie/apps/context_processors.py
irie/apps/sitemaps.py
irie/apps/admin_dash/__init__.py
irie/apps/admin_dash/admin.py
irie/apps/admin_dash/apps.py
irie/apps/admin_dash/forms.py
irie/apps/admin_dash/models.py
irie/apps/admin_dash/urls.py
irie/apps/admin_dash/utils.py
irie/apps/admin_dash/views.py
irie/apps/admin_dash/templatetags/__init__.py
irie/apps/admin_dash/templatetags/admin_material.py
irie/apps/admin_dash/templatetags/replace_value.py
irie/apps/authentication/__init__.py
irie/apps/authentication/admin.py
irie/apps/authentication/config.py
irie/apps/authentication/forms.py
irie/apps/authentication/models.py
irie/apps/authentication/tests.py
irie/apps/authentication/urls.py
irie/apps/authentication/views.py
irie/apps/authentication/migrations/__init__.py
irie/apps/documents/__init__.py
irie/apps/documents/apps.py
irie/apps/documents/documents.py
irie/apps/documents/tests.py
irie/apps/documents/urls.py
irie/apps/documents/views.py
irie/apps/documents/migrations/__init__.py
irie/apps/evaluation/__init__.py
irie/apps/evaluation/admin.py
irie/apps/evaluation/apps.py
irie/apps/evaluation/daemon.py
irie/apps/evaluation/identification.py
irie/apps/evaluation/models.py
irie/apps/evaluation/urls.py
irie/apps/evaluation/views.py
irie/apps/evaluation/migrations/0001_initial.py
irie/apps/evaluation/migrations/0002_evaluation_status.py
irie/apps/evaluation/migrations/__init__.py
irie/apps/events/__init__.py
irie/apps/events/admin.py
irie/apps/events/apps.py
irie/apps/events/filters.py
irie/apps/events/models.py
irie/apps/events/tests.py
irie/apps/events/tests_events.py
irie/apps/events/urls.py
irie/apps/events/views.py
irie/apps/events/views_events.py
irie/apps/events/earthquake/models.py
irie/apps/events/migrations/0001_initial.py
irie/apps/events/migrations/0002_rename_event_eventrecord.py
irie/apps/events/migrations/0003_hazardevent.py
irie-0.0.68.dist-info/METADATA
irie-0.0.68.dist-info/WHEEL
irie-0.0.68.dist-info/entry_points.txt
irie-0.0.68.dist-info/top_level.txt
irie-0.0.68.dist-info/RECORD
