Metadata-Version: 2.4
Name: irie
Version: 0.0.68
Summary: An infrastructure resilience engine
Author-email: "Claudio M. Perez" <50180406+claudioperez@users.noreply.github.com>
Project-URL: Repository, https://github.com/STAIRLab
Project-URL: Documentation, https://stairlab.berkeley.edu/software/irie/
Keywords: resilience,structural-health-monitoring,finite-element-analysis,xara
Classifier: Development Status :: 4 - Beta
Classifier: Intended Audience :: Science/Research
Classifier: Intended Audience :: Developers
Classifier: Programming Language :: C
Classifier: Programming Language :: Python
Classifier: Programming Language :: Python :: 3
Classifier: Programming Language :: Python :: 3.7
Classifier: Programming Language :: Python :: 3.8
Classifier: Programming Language :: Python :: 3.9
Classifier: Programming Language :: Python :: 3.10
Classifier: Programming Language :: Python :: 3.11
Classifier: Programming Language :: Python :: 3.12
Classifier: Programming Language :: Python :: 3 :: Only
Classifier: Topic :: Software Development
Classifier: Topic :: Scientific/Engineering
Classifier: Operating System :: Microsoft :: Windows
Classifier: Operating System :: POSIX
Classifier: Operating System :: Unix
Classifier: Operating System :: MacOS
Requires-Dist: opensees>=0.1.0
Requires-Dist: quakeio
Requires-Dist: veux>=0.0.40
Requires-Dist: xara>=0.0.8
Requires-Dist: xcsi>=0.0.5
Requires-Dist: mdof
Requires-Dist: xsection>=0.0.20
Requires-Dist: openbim
Requires-Dist: openpyxl
Requires-Dist: tqdm
Requires-Dist: folium
Requires-Dist: pandas
Requires-Dist: numpy
Requires-Dist: orjson
Requires-Dist: jsonschema
Requires-Dist: beautifulsoup4
Requires-Dist: autopep8
Requires-Dist: Django==5.2.2
Requires-Dist: asgiref==3.8.1
Requires-Dist: gunicorn==23.0.0
Requires-Dist: pytz==2021.3
Requires-Dist: sqlparse==0.5.1
Requires-Dist: toml>=0.10.2
Requires-Dist: whitenoise==5.3.0
Requires-Dist: crispy-bootstrap5
Requires-Dist: django-filter
Requires-Dist: django-crispy-forms
Requires-Dist: django-environ==0.11.2
Requires-Dist: djangorestframework==3.15.2
Requires-Dist: djangorestframework-simplejwt==5.3.1
Requires-Dist: dj-database-url==2.1.0
Requires-Dist: django-formtools
